cmverify/__init__.py
cmverify/annotation.py
cmverify/config.py
cmverify/core.py
cmverify/models.py
cmverify/utils.py
cmverify/viz.py
cmverify/models/AIFI_rf_best_estimator.pkl
cmverify/models/ref_pbmc_clean_celltypist_model_AIFI_L3_2024-04-19.pkl
cmverify/models/rf_scaler.pkl
cmverify-1.0.3.dist-info/licenses/LICENSE
cmverify-1.0.3.dist-info/METADATA
cmverify-1.0.3.dist-info/WHEEL
cmverify-1.0.3.dist-info/top_level.txt
cmverify-1.0.3.dist-info/RECORD
