Metadata-Version: 2.4
Name: CMVerify
Version: 1.0.3
Summary: CMV serostatus predictor using scRNA-seq data
Author-email: Luke Trinity <luke.trinity@jax.org>
License-Expression: AGPL-3.0-only
Project-URL: Homepage, https://ucarlab.github.io/
Classifier: Programming Language :: Python :: 3
Classifier: Operating System :: OS Independent
Requires-Python: >=3.8
License-File: LICENSE
Requires-Dist: scanpy
Requires-Dist: matplotlib
Requires-Dist: anndata
Requires-Dist: celltypist
Requires-Dist: ipython
Requires-Dist: joblib
Requires-Dist: numpy
Requires-Dist: pandas
Requires-Dist: seaborn
Requires-Dist: scikit-learn
Dynamic: license-file
